{
  "docId": "210211_70.json",
  "GL_Text": "Про передачу громадянці Баклан Антоніні Олегівні у приватну власність земельної ділянки для будівництва і обслуговування жилого будинку, господарських будівель і споруд у пров. Лозовому, 6 у Деснянському районі міста Києва (422282210). (Від 17.03.2020 № 08/231-651/ПР).\nпро передачу громадянину Венедіктову Володимиру Івановичу у власність земельної ділянки для ведення колективного садівництва на вул. 5-тій Озерній, будинок 2 у Дарницькому районі міста Києва (579029566). (Від 30.06.2020 № 08/231-1636/ПР), про передачу громадянину Ісрафілову Відаді Шахліяр Огли у приватну власність земельної ділянки для будівництва і обслуговування жилого будинку, господарських будівель і споруд на вул. Цілинній, 34-В у Голосіївському районі міста Києва (678292784). (Від 07.08.2020 № 08/231-2002/ПР).",
  "YESCnt": 98,
  "NOCnt": 0,
  "UTRCnt": 0,
  "NGCnt": 7,
  "TotalCnt": 105,
  "RESULT": "РІШЕННЯ ПРИЙНЯТЕ",
  "ABSCnt": 17,
  "TotalInclAbsCnt": 122
}