{
  "docId": "210708_121.json",
  "DocTime": "08.07.21",
  "GL_Text": "Про надання Київському комунальному об’єднанню зеленого будівництва та експлуатації зелених насаджень міста «Київзеленбуд» дозволу на розроблення проєкту землеустрою щодо відведення земельної ділянки у постійне користування для обслуговування та експлуатації зелених насаджень загального користування між будинками № 4 та № 8 у пров. К. Гордієнка у Печерському районі міста Києва (571701641). (Від 31.01.2020 № 08/231-253/ПР).",
  "YESCnt": 88,
  "NOCnt": 0,
  "UTRCnt": 0,
  "NGCnt": 7,
  "TotalCnt": 95,
  "RESULT": "РІШЕННЯ ПРИЙНЯТЕ",
  "ABSCnt": 26,
  "TotalInclAbsCnt": 121
}