{
  "docId": "210708_118.json",
  "DocTime": "08.07.21",
  "GL_Text": "Про надання Київському комунальному об’єднанню зеленого будівництва та експлуатації зелених насаджень міста «Київзеленбуд» дозволу на розроблення проекту землеустрою щодо відведення в постійне користування земельної ділянки для утримання та благоустрою зелених зон і зелених насаджень та обслуговування скверу на просп. Лісовому, 4-а у Деснянському районі міста Києва (512501177). (Від 22.11.2019 № 08/231-3565/ПР).",
  "YESCnt": 90,
  "NOCnt": 0,
  "UTRCnt": 0,
  "NGCnt": 8,
  "TotalCnt": 98,
  "RESULT": "РІШЕННЯ ПРИЙНЯТЕ",
  "ABSCnt": 23,
  "TotalInclAbsCnt": 121
}