{
  "docId": "210831_145.json",
  "DocTime": "31.08.2021 21:21:47",
  "GL_Text": "За основу питання порядку денного про поновлення приватному акціонерному товариству «Дарницький комбінат будівельних матеріалів і конструкцій» договору оренди земельних ділянок від 21 березня 2006 року № 66-6-00328 (зі змінами) (598105247). (Від 01.04.2021 № 08/231-1168/ПР).",
  "YESCnt": 60,
  "NOCnt": 7,
  "UTRCnt": 2,
  "NGCnt": 27,
  "TotalCnt": 96,
  "RESULT": "РІШЕННЯ НЕ ПРИЙНЯТЕ",
  "ABSCnt": 25,
  "TotalInclAbsCnt": 121
}