{
  "docId": "211007_105.json",
  "DocTime": "07.10.2021 18:59:57",
  "GL_Text": "Про передачу ТОВАРИСТВУ З ОБМЕЖЕНОЮ ВІДПОВІДАЛЬНІСТЮ «УКРАЇНСЬКІ ІНЖЕНЕРНІ СИСТЕМИ РОЗВИТКУ ПЛЮС» земельної ділянки в оренду для експлуатації та обслуговування нежитлового будинку на вул. Канальній, 1-а у Дарницькому районі міста Києва (354399501). (Від 17.09.2021 № 08/231-3412/ПР)",
  "YESCnt": 96,
  "NOCnt": 0,
  "UTRCnt": 0,
  "NGCnt": 5,
  "TotalCnt": 101,
  "RESULT": "РІШЕННЯ ПРИЙНЯТЕ",
  "ABSCnt": 20,
  "TotalInclAbsCnt": 121
}