{
  "docId": "211007_115.json",
  "DocTime": "07.10.2021 18:59:56",
  "GL_Text": "Про надання громадянину Смірнову Володимиру Васильовичу дозволу на розроблення проєкту землеустрою щодо відведення земельної ділянки у власність для будівництва і обслуговування жилого будинку, господарських будівель і споруд на вул. Прикордонній, 22 у Деснянському районі міста Києва (677650107). (На виконання постанови Окружного адміністративного суду міста Києва від 22.06.2018 у справі № 826/17768/17). (Від 08.12.2020 № 08/231-96/ПР)",
  "YESCnt": 16,
  "NOCnt": 0,
  "UTRCnt": 28,
  "NGCnt": 49,
  "TotalCnt": 93,
  "RESULT": "РІШЕННЯ НЕ ПРИЙНЯТЕ",
  "ABSCnt": 28,
  "TotalInclAbsCnt": 121
}