{
  "docId": "220120_17.json",
  "GL_Text": "За зміну черговості розгляду питання порядку денного про створення Тимчасової контрольної комісії Київської міської ради з питань перевірки обґрунтованості та причин зміни термінів будівництва дільниці Сирецько-Печерської лінії метрополітену на житловий масив Виноградар (Від 12.10.2021 08/231-3728/ПР)",
  "YESCnt": 21,
  "NOCnt": 2,
  "UTRCnt": 21,
  "NGCnt": 33,
  "TotalCnt": 77,
  "RESULT": "РІШЕННЯ НЕ ПРИЙНЯТЕ",
  "ABSCnt": 44,
  "TotalInclAbsCnt": 121
}