{
  "docId": "220623_138.json",
  "GL_Text": "Про надання згоди на передачу права власності на земельну ділянку для будівництва та обслуговування житлового будинку, господарських будівель і споруд у пров. 2-му Садовому, 4 у Деснянському районі міста Києва у комунальну власність територіальної громади міста Києва (613992763). (Від 26.01.2022 № 08/231-219/ПР)",
  "YESCnt": 69,
  "NOCnt": 0,
  "UTRCnt": 0,
  "NGCnt": 7,
  "TotalCnt": 76,
  "RESULT": "РІШЕННЯ ПРИЙНЯТЕ",
  "ABSCnt": 45,
  "TotalInclAbsCnt": 121
}