{
  "docId": "220908_58.json",
  "GL_Text": "Про безоплатне прийняття до комунальної власності територіальної громади міста Києва гуртожитку та зовнішніх інженерних мереж Приватного акціонерного товариства «ФАНЕРИ ТА ПЛИТИ» та внесення змін у додаток до рішення Київської міської ради від 24 травня 2012 року № 596/7933 «Про приватизацію жилих приміщень у гуртожитках м. Києва». (Від 12.07.2022 № 08/231-876/ПР)",
  "YESCnt": 79,
  "NOCnt": 0,
  "UTRCnt": 0,
  "NGCnt": 8,
  "TotalCnt": 87,
  "RESULT": "РІШЕННЯ ПРИЙНЯТЕ",
  "ABSCnt": 34,
  "TotalInclAbsCnt": 121
}