{
  "docId": "230518_211.json",
  "DocTime": "22.05.2023 12:47:16",
  "GL_Text": "Про зміну цільового призначення земельної ділянки, що перебуває в оренді приватного підприємства «Клініка Медіком», для експлуатації та обслуговування медичного центру на Оболонській набережній, 9 в Оболонському районі міста Києва та внесення змін до договору оренди (383955231). (від 30.01.2023 № 08/231-138/ПР).",
  "YESCnt": 71,
  "NOCnt": 0,
  "UTRCnt": 0,
  "NGCnt": 7,
  "TotalCnt": 78,
  "RESULT": "РІШЕННЯ ПРИЙНЯТЕ",
  "ABSCnt": 43,
  "TotalInclAbsCnt": 121
}