{
  "docId": "231102_18.json",
  "DocTime": "02.11.2023 17:47:18",
  "GL_Text": "Про надання обслуговуючому кооперативу «ЖБК Україна» дозволу на розроблення проекту землеустрою щодо відведення земельної ділянки у постійне користування для обслуговування багатоквартирного житлового будинку на вул. Юліуса Фучика, 8 у Солом’янському районі міста Києва (201882870). (від 09.09.2019 № 08/231-2761/ПР).",
  "YESCnt": 81,
  "NOCnt": 0,
  "UTRCnt": 0,
  "NGCnt": 8,
  "TotalCnt": 89,
  "RESULT": "РІШЕННЯ ПРИЙНЯТЕ",
  "ABSCnt": 32,
  "TotalInclAbsCnt": 121
}