{
  "DocTime": "11.02.21",
  "OrgName": "КИЇВСЬКА МІСЬКА РАДА",
  "SName": "Пленарне засідання  2 сесія  9 скликання",
  "GLType": "ПОІМЕННЕ ГОЛОСУВАННЯ",
  "GLTime": "11.02.21 17:17",
  "PD_NPP": "68",
  "PD_Fullname": "За повернення до розгляду питання порядку денного про приватизацію громадянином Іщенком Олегом Віталійовичем земельної ділянки для будівництва і обслуговування жилого будинку, господарських будівель і споруд на Оболонській набережній, 71 в Оболонському районі міста Києва (418289573). (Від 12.06.2020 № 08/231-1469/ПР).",
  "GL_Text": "За повернення до розгляду питання порядку денного про приватизацію громадянином Іщенком Олегом Віталійовичем земельної ділянки для будівництва і обслуговування жилого будинку, господарських будівель і споруд на Оболонській набережній, 71 в Оболонському районі міста Києва (418289573). (Від 12.06.2020 № 08/231-1469/ПР).",
  "GL_ResultType": " ",
  "DPList": [
    {
      "DPName": "Андронов В. Є.",
      "DPGolos": "За"
    },
    {
      "DPName": "Андрусишин В. Й.",
      "DPGolos": "За"
    },
    {
      "DPName": "Ар'єва Я. В.",
      "DPGolos": "За"
    },
    {
      "DPName": "Артеменко  С. В.",
      "DPGolos": "За"
    },
    {
      "DPName": "Ахметов Р. С.",
      "DPGolos": "..."
    },
    {
      "DPName": "Баленко  І. М.",
      "DPGolos": "За"
    },
    {
      "DPName": "Банас  Д. М.",
      "DPGolos": "За"
    },
    {
      "DPName": "Берікашвілі Н. В.",
      "DPGolos": "За"
    },
    {
      "DPName": "Білоцерковець Д. О.",
      "DPGolos": "За"
    },
    {
      "DPName": "Богатов  К. В.",
      "DPGolos": "Проти"
    },
    {
      "DPName": "Бойченко П. І.",
      "DPGolos": "..."
    },
    {
      "DPName": "Бондаренко В. В.",
      "DPGolos": "За"
    },
    {
      "DPName": "Брагінський В. В.",
      "DPGolos": "За"
    },
    {
      "DPName": "Бровченко К. М.",
      "DPGolos": "..."
    },
    {
      "DPName": "Бродський  О. Я.",
      "DPGolos": "..."
    },
    {
      "DPName": "Букало О. Ю.",
      "DPGolos": "..."
    },
    {
      "DPName": "Бурдукова В. В.",
      "DPGolos": "Не голосував"
    },
    {
      "DPName": "Васильчук  В. В.",
      "DPGolos": "Утримався"
    },
    {
      "DPName": "Веремеєнко  О. Л.",
      "DPGolos": "Не голосував"
    },
    {
      "DPName": "Вітренко А. О.",
      "DPGolos": "Не голосував"
    },
    {
      "DPName": "Габібуллаєва Д. Т.",
      "DPGolos": "За"
    },
    {
      "DPName": "Галайчук  І. В.",
      "DPGolos": "..."
    },
    {
      "DPName": "Говорова О. І.",
      "DPGolos": "Не голосував"
    },
    {
      "DPName": "Гончаров  В. В.",
      "DPGolos": "За"
    },
    {
      "DPName": "Гончаров  О. В.",
      "DPGolos": "За"
    },
    {
      "DPName": "Грушко  В. В.",
      "DPGolos": "За"
    },
    {
      "DPName": "Ємець Л. О.",
      "DPGolos": "Не голосував"
    },
    {
      "DPName": "Задерейко  А. І.",
      "DPGolos": "За"
    },
    {
      "DPName": "Зантарая Г. М.",
      "DPGolos": "Не голосував"
    },
    {
      "DPName": "Зубко  Ю. Г.",
      "DPGolos": "Не голосував"
    },
    {
      "DPName": "Зубрицька О. М.",
      "DPGolos": "За"
    },
    {
      "DPName": "Іванченко  В. А.",
      "DPGolos": "За"
    },
    {
      "DPName": "Іщенко  М. В.",
      "DPGolos": "За"
    },
    {
      "DPName": "Калініченко  Д. Ю.",
      "DPGolos": "За"
    },
    {
      "DPName": "Кириленко І. І.",
      "DPGolos": "Не голосував"
    },
    {
      "DPName": "Кириченко К. В.",
      "DPGolos": "Не голосував"
    },
    {
      "DPName": "Кличко  В. В.",
      "DPGolos": "..."
    },
    {
      "DPName": "Ковалевська Л. О.",
      "DPGolos": "За"
    },
    {
      "DPName": "Коваленко Г. М.",
      "DPGolos": "За"
    },
    {
      "DPName": "Ковальчук М. М.",
      "DPGolos": "..."
    },
    {
      "DPName": "Козак Т. М.",
      "DPGolos": "..."
    },
    {
      "DPName": "Кононенко В. І.",
      "DPGolos": "За"
    },
    {
      "DPName": "Конопелько М. В.",
      "DPGolos": "Не голосував"
    },
    {
      "DPName": "Костюшко  О. П.",
      "DPGolos": "За"
    },
    {
      "DPName": "Кравець В. А.",
      "DPGolos": "За"
    },
    {
      "DPName": "Криворучко  Т. Г.",
      "DPGolos": "За"
    },
    {
      "DPName": "Кримчак  С. О.",
      "DPGolos": "За"
    },
    {
      "DPName": "Кузьменко Є. А.",
      "DPGolos": "Не голосував"
    },
    {
      "DPName": "Кулеба Є. А.",
      "DPGolos": "Утримався"
    },
    {
      "DPName": "Кушнір І. І.",
      "DPGolos": "0"
    },
    {
      "DPName": "Левченко О. А.",
      "DPGolos": "За"
    },
    {
      "DPName": "Лимар Ю. В.",
      "DPGolos": "За"
    },
    {
      "DPName": "Лінчевський О. В.",
      "DPGolos": "Утримався"
    },
    {
      "DPName": "Макаренко М. А.",
      "DPGolos": "За"
    },
    {
      "DPName": "Маленко Г. С.",
      "DPGolos": "Утримався"
    },
    {
      "DPName": "Маляревич  О. В.",
      "DPGolos": "За"
    },
    {
      "DPName": "Мамоян С. Ч.",
      "DPGolos": "Не голосував"
    },
    {
      "DPName": "Марченко О. Л.",
      "DPGolos": "Не голосував"
    },
    {
      "DPName": "Михайлова А. А.",
      "DPGolos": "Утримався"
    },
    {
      "DPName": "Міщенко  О. Г.",
      "DPGolos": "За"
    },
    {
      "DPName": "Мондриївський  В. М.",
      "DPGolos": "За"
    },
    {
      "DPName": "Москаль  Д. Д.",
      "DPGolos": "Не голосував"
    },
    {
      "DPName": "Муха  В. В.",
      "DPGolos": "За"
    },
    {
      "DPName": "Наконечний М. В.",
      "DPGolos": "Не голосував"
    },
    {
      "DPName": "Непоп  В. І.",
      "DPGolos": "..."
    },
    {
      "DPName": "Нестор В. Р.",
      "DPGolos": "Не голосував"
    },
    {
      "DPName": "Нефьодов М. Є.",
      "DPGolos": "Утримався"
    },
    {
      "DPName": "Никорак  І. П.",
      "DPGolos": "За"
    },
    {
      "DPName": "Овраменко  О. В.",
      "DPGolos": "За"
    },
    {
      "DPName": "Окопний  О. Ю.",
      "DPGolos": "За"
    },
    {
      "DPName": "Омельченко  О. О.",
      "DPGolos": "За"
    },
    {
      "DPName": "Опадчий  І. М.",
      "DPGolos": "За"
    },
    {
      "DPName": "Павлик  В. А.",
      "DPGolos": "За"
    },
    {
      "DPName": "Пастухова Н. Ю.",
      "DPGolos": "За"
    },
    {
      "DPName": "Пашинна Л. В.",
      "DPGolos": "Утримався"
    },
    {
      "DPName": "Петрівська Л. С.",
      "DPGolos": "За"
    },
    {
      "DPName": "Пинзеник  О. О.",
      "DPGolos": "..."
    },
    {
      "DPName": "Плужник О. А.",
      "DPGolos": "..."
    },
    {
      "DPName": "Погребиський О. І.",
      "DPGolos": "За"
    },
    {
      "DPName": "Попатенко В. С.",
      "DPGolos": "Утримався"
    },
    {
      "DPName": "Попов О. П.",
      "DPGolos": "Не голосував"
    },
    {
      "DPName": "Порайко А. М.",
      "DPGolos": "За"
    },
    {
      "DPName": "Порошенко М. А.",
      "DPGolos": "За"
    },
    {
      "DPName": "Присяжнюк М. О.",
      "DPGolos": "Не голосував"
    },
    {
      "DPName": "Прокопів  В. В.",
      "DPGolos": "За"
    },
    {
      "DPName": "Романюк Р. С.",
      "DPGolos": "За"
    },
    {
      "DPName": "Самолудченко О. А.",
      "DPGolos": "Не голосував"
    },
    {
      "DPName": "Свириденко  Г. В.",
      "DPGolos": "..."
    },
    {
      "DPName": "Семенова К. І.",
      "DPGolos": "Утримався"
    },
    {
      "DPName": "Симуніна Ю. М.",
      "DPGolos": "Не голосував"
    },
    {
      "DPName": "Слончак В. В.",
      "DPGolos": "Не голосував"
    },
    {
      "DPName": "Смірнова М. М.",
      "DPGolos": "За"
    },
    {
      "DPName": "Старостенко  Г. В.",
      "DPGolos": "..."
    },
    {
      "DPName": "Сторожук  В. П.",
      "DPGolos": "За"
    },
    {
      "DPName": "Странніков  А. М.",
      "DPGolos": "За"
    },
    {
      "DPName": "Сулига  Ю. А.",
      "DPGolos": "..."
    },
    {
      "DPName": "Супрун О. С.",
      "DPGolos": "За"
    },
    {
      "DPName": "Таран С. В.",
      "DPGolos": "Не голосував"
    },
    {
      "DPName": "Терентьєв  М. О.",
      "DPGolos": "За"
    },
    {
      "DPName": "Тимощук Б. А.",
      "DPGolos": "Не голосував"
    },
    {
      "DPName": "Тимченко О. С.",
      "DPGolos": "..."
    },
    {
      "DPName": "Тихонович Ю. С.",
      "DPGolos": "За"
    },
    {
      "DPName": "Товмасян  В. Р.",
      "DPGolos": "Не голосував"
    },
    {
      "DPName": "Трубіцин В. С.",
      "DPGolos": "Проти"
    },
    {
      "DPName": "Турець  В. В.",
      "DPGolos": "За"
    },
    {
      "DPName": "Уласик Ю. О.",
      "DPGolos": "Не голосував"
    },
    {
      "DPName": "Усов К. Г.",
      "DPGolos": "..."
    },
    {
      "DPName": "Федоренко Ю. С.",
      "DPGolos": "Утримався"
    },
    {
      "DPName": "Федоренко Я. Ю.",
      "DPGolos": "За"
    },
    {
      "DPName": "Хацевич І. М.",
      "DPGolos": "За"
    },
    {
      "DPName": "Царенко М. О.",
      "DPGolos": "Не голосував"
    },
    {
      "DPName": "Чайка О. Ю.",
      "DPGolos": "За"
    },
    {
      "DPName": "Чорній Б. П.",
      "DPGolos": "За"
    },
    {
      "DPName": "Шаповал А. А.",
      "DPGolos": "Не голосував"
    },
    {
      "DPName": "Шлапак  А. В.",
      "DPGolos": "..."
    },
    {
      "DPName": "Шовковський О. В.",
      "DPGolos": "За"
    },
    {
      "DPName": "Шпак І. В.",
      "DPGolos": "За"
    },
    {
      "DPName": "Яловий  В. Б.",
      "DPGolos": "..."
    },
    {
      "DPName": "Ярмоленко  Ю. О.",
      "DPGolos": "За"
    },
    {
      "DPName": "Ярош З. В.",
      "DPGolos": "Утримався"
    },
    {
      "DPName": "Ярошенко  Р. В.",
      "DPGolos": "За"
    },
    {
      "DPName": "Ясинський  Г. І.",
      "DPGolos": "За"
    }
  ],
  "YESCnt": 62,
  "NOCnt": 2,
  "UTRCnt": 11,
  "NGCnt": 27,
  "TotalCnt": 102,
  "RESULT": "Рішення ПРИЙНЯТЕ"
}